__init__.py
pyelement/__init__.py
pyelement/v3/__init__.py
pyelement/v3/element.py
pyelement-0.0.1b2.dist-info/LICENSE
pyelement-0.0.1b2.dist-info/METADATA
pyelement-0.0.1b2.dist-info/WHEEL
pyelement-0.0.1b2.dist-info/top_level.txt
pyelement-0.0.1b2.dist-info/RECORD
