Metadata-Version: 2.1
Name: pyelement
Version: 0.0.1b2
Summary: Sends message to Element messanger
Author-email: Konstantin Suspitsyn <konstantin.suspitsun@xmail.ru>
Project-URL: Homepage, https://github.com/konstantin-suspitsyn/pyelement
Project-URL: Issues, https://github.com/konstantin-suspitsyn/pyelement/issues
Classifier: Development Status :: 4 - Beta
Classifier: Programming Language :: Python :: 3
Classifier: License :: OSI Approved :: Apache Software License
Classifier: Operating System :: Microsoft :: Windows
Requires-Python: >=3.9
License-File: LICENSE
Requires-Dist: requests==2.32.3
